mesibo/__init__.py
mesibo/version.py
mesibo/clib/linux/aarch64/libmesibo.so
mesibo/clib/linux/aarch64/libmesibo.sum
mesibo/clib/linux/aarch64/3.10/_mesibo.so
mesibo/clib/linux/aarch64/3.10/_mesibo.sum
mesibo/clib/linux/aarch64/3.11/_mesibo.so
mesibo/clib/linux/aarch64/3.11/_mesibo.sum
mesibo/clib/linux/aarch64/3.12/_mesibo.so
mesibo/clib/linux/aarch64/3.12/_mesibo.sum
mesibo/clib/linux/aarch64/3.13/_mesibo.so
mesibo/clib/linux/aarch64/3.13/_mesibo.sum
mesibo/clib/linux/aarch64/3.9/_mesibo.so
mesibo/clib/linux/aarch64/3.9/_mesibo.sum
mesibo/clib/linux/x86_64/libmesibo.so
mesibo/clib/linux/x86_64/libmesibo.sum
mesibo/clib/linux/x86_64/3.10/_mesibo.so
mesibo/clib/linux/x86_64/3.10/_mesibo.sum
mesibo/clib/linux/x86_64/3.11/_mesibo.so
mesibo/clib/linux/x86_64/3.11/_mesibo.sum
mesibo/clib/linux/x86_64/3.12/_mesibo.so
mesibo/clib/linux/x86_64/3.12/_mesibo.sum
mesibo/clib/linux/x86_64/3.13/_mesibo.so
mesibo/clib/linux/x86_64/3.13/_mesibo.sum
mesibo/clib/linux/x86_64/3.9/_mesibo.so
mesibo/clib/linux/x86_64/3.9/_mesibo.sum
mesibo/clib/macos/arm64/libmesibo.so
mesibo/clib/macos/arm64/libmesibo.sum
mesibo/clib/macos/arm64/3.10/_mesibo.so
mesibo/clib/macos/arm64/3.10/_mesibo.sum
mesibo/clib/macos/arm64/3.11/_mesibo.so
mesibo/clib/macos/arm64/3.11/_mesibo.sum
mesibo/clib/macos/arm64/3.12/_mesibo.so
mesibo/clib/macos/arm64/3.12/_mesibo.sum
mesibo/clib/macos/arm64/3.13/_mesibo.so
mesibo/clib/macos/arm64/3.13/_mesibo.sum
mesibo/clib/macos/arm64/3.9/_mesibo.so
mesibo/clib/macos/arm64/3.9/_mesibo.sum
mesibo/clib/macos/x86_64/libmesibo.so
mesibo/clib/macos/x86_64/libmesibo.sum
mesibo/clib/macos/x86_64/3.10/_mesibo.so
mesibo/clib/macos/x86_64/3.10/_mesibo.sum
mesibo/clib/macos/x86_64/3.11/_mesibo.so
mesibo/clib/macos/x86_64/3.11/_mesibo.sum
mesibo/clib/macos/x86_64/3.12/_mesibo.so
mesibo/clib/macos/x86_64/3.12/_mesibo.sum
mesibo/clib/macos/x86_64/3.13/_mesibo.so
mesibo/clib/macos/x86_64/3.13/_mesibo.sum
mesibo/clib/macos/x86_64/3.9/_mesibo.so
mesibo/clib/macos/x86_64/3.9/_mesibo.sum
mesibo-2.7.1.dist-info/METADATA
mesibo-2.7.1.dist-info/WHEEL
mesibo-2.7.1.dist-info/top_level.txt
mesibo-2.7.1.dist-info/RECORD
