Metadata-Version: 2.1
Name: mesibo
Version: 2.7.1
Summary: mesibo is a real-time communication platform with APIs for messaging and calls
Home-page: https://github.com/mesibo/python
Author: https://mesibo.com
Author-email: support@mesibo.com
Project-URL: Bug Tracker, https://github.com/mesibo/python/issues
Classifier: Development Status :: 5 - Production/Stable
Classifier: Intended Audience :: Developers
Classifier: Operating System :: Unix
Classifier: Programming Language :: Python
Classifier: Programming Language :: Python :: 3
Classifier: Topic :: Software Development :: Libraries :: Python Modules
Requires-Python: >=3.6
